bytewax_webflow/__init__.py
bytewax_webflow/py.typed
bytewax_webflow/types.py
bytewax_webflow/webflow_client.py
bytewax_webflow/inputs/__init__.py
bytewax_webflow/outputs/__init__.py
bytewax_webflow/outputs/collection_item_sink.py
bytewax_webflow-0.3.3.dist-info/METADATA
bytewax_webflow-0.3.3.dist-info/WHEEL
bytewax_webflow-0.3.3.dist-info/licenses/LICENSE
bytewax_webflow-0.3.3.dist-info/RECORD
