Metadata-Version: 2.3
Name: bytewax-webflow
Version: 0.3.3
Summary: Webflow connectors for Bytewax
Project-URL: Repository, https://github.com/imnotjames/bytewax-webflow.git
Project-URL: Issues, https://github.com/imnotjames/bytewax-webflow/issues
Author-email: James Ward <james@notjam.es>
License: MIT License
Keywords: bytewax,webflow
Requires-Python: >=3.12
Requires-Dist: bytewax>=0.21.0
Requires-Dist: requests>=2.32.3
